open_journal-1.1.1.data/scripts/main.py
openjournal/__init__.py
openjournal/main.py
openjournal/ui/AboutWindow.py
openjournal/ui/MainWindow.py
openjournal/ui/__init__.py
openjournal/ui/resources_rc.py
open_journal-1.1.1.dist-info/LICENSE
open_journal-1.1.1.dist-info/METADATA
open_journal-1.1.1.dist-info/WHEEL
open_journal-1.1.1.dist-info/entry_points.txt
open_journal-1.1.1.dist-info/top_level.txt
open_journal-1.1.1.dist-info/RECORD
