Metadata-Version: 2.1
Name: open-journal
Version: 1.1.1
Summary: A simple, private, open-source journal.
Home-page: https://github.com/Optimizer-Prime/open-journal
Author: Stuart Clayton
Author-email: stu3cla@pm.me
License: GPL-3.0
Platform: UNKNOWN
Classifier: Programming Language :: Python :: 3
Requires-Python: >=3.6
Requires-Dist: pyqt5
Requires-Dist: cryptography
Requires-Dist: continuous-threading
